AUTHORS
CHANGELOG
LICENSE
MANIFEST.in
README.rst
VERSION
setup.py
django_i18nurl.egg-info/PKG-INFO
django_i18nurl.egg-info/SOURCES.txt
django_i18nurl.egg-info/dependency_links.txt
django_i18nurl.egg-info/not-zip-safe
django_i18nurl.egg-info/top_level.txt
i18nurl/__init__.py
i18nurl/context_processors.py
i18nurl/forms.py
i18nurl/middleware.py
i18nurl/models.py
i18nurl/settings.py
i18nurl/urls.py
i18nurl/utils.py
i18nurl/views.py
i18nurl/templates/i18n/base.html
i18nurl/templates/i18n/set_language.html
i18nurl/templatetags/__init__.py
i18nurl/templatetags/i18nurl.py