Metadata-Version: 1.1
Name: django-i18nurl
Version: 0.1
Summary: Django i18n URL
Home-page: https://github.com/novagile/django-i18nurl
Author: Rémy Hubscher
Author-email: hubscher.remy@gmail.com
License: BSD Licence
Keywords: d,j,a,n,g,o, ,i,1,8,n, ,u,r,l
Platform: UNKNOWN
Classifier: Development Status :: 3 - Alpha
Classifier: Environment :: Web Environment
Classifier: Framework :: Django
Classifier: Intended Audience :: Developers
Classifier: License :: OSI Approved :: BSD License
Classifier: Natural Language :: English
Classifier: Programming Language :: Python
Classifier: Programming Language :: Python :: 3
